phantasy_machines/__init__.py
phantasy_machines/ARIS/phantasy.ini
phantasy_machines/ARIS/f1/Makefile
phantasy_machines/ARIS/f1/baseline.lat
phantasy_machines/ARIS/f1/layout.csv
phantasy_machines/ARIS/f1/phantasy.cfg
phantasy_machines/ARIS/f1/settings.json
phantasy_machines/ARIS/f1/template.lat
phantasy_machines/ARIS/f1/flame_data/envelope.txt
phantasy_machines/ARIS/f1/flame_data/position.txt
phantasy_machines/ARIS/f2/channels.csv
phantasy_machines/ARIS/f2/layout.csv
phantasy_machines/ARIS/f2/phantasy.cfg
phantasy_machines/ARIS/f2/pspvconfig.csv
phantasy_machines/ARIS/f2/settings.json
phantasy_machines/ARIS/presp/ARIS_F1_misalignment_sheet_example.xlsx
phantasy_machines/ARIS/presp/Makefile
phantasy_machines/ARIS/presp/README.md
phantasy_machines/ARIS/presp/baseline.lat
phantasy_machines/ARIS/presp/channels.csv
phantasy_machines/ARIS/presp/clean_settings.py
phantasy_machines/ARIS/presp/layout.csv
phantasy_machines/ARIS/presp/phantasy.cfg
phantasy_machines/ARIS/presp/pspvconfig.csv
phantasy_machines/ARIS/presp/pv-stats.dat
phantasy_machines/ARIS/presp/settings.json
phantasy_machines/ARIS/presp/flame_data/envelope.txt
phantasy_machines/ARIS/presp/flame_data/position.txt
phantasy_machines/ARIS_VA/phantasy.ini
phantasy_machines/ARIS_VA/presp/ARIS_F1_misalignment_sheet_example.xlsx
phantasy_machines/ARIS_VA/presp/Makefile
phantasy_machines/ARIS_VA/presp/PSv08_v1.3test.lat
phantasy_machines/ARIS_VA/presp/README.md
phantasy_machines/ARIS_VA/presp/baseline.lat
phantasy_machines/ARIS_VA/presp/channels.csv
phantasy_machines/ARIS_VA/presp/layout.csv
phantasy_machines/ARIS_VA/presp/phantasy.cfg
phantasy_machines/ARIS_VA/presp/pspvconfig.csv
phantasy_machines/ARIS_VA/presp/settings.json
phantasy_machines/ARIS_VA/presp/flame_data/envelope.txt
phantasy_machines/ARIS_VA/presp/flame_data/position.txt
phantasy_machines/ARIS_VA/presp/notebooks/beam_ellipse.ipynb
phantasy_machines/ARIS_VA/presp/notebooks/test_lattice.ipynb
phantasy_machines-6.1.3.dist-info/LICENSE
phantasy_machines-6.1.3.dist-info/METADATA
phantasy_machines-6.1.3.dist-info/WHEEL
phantasy_machines-6.1.3.dist-info/top_level.txt
phantasy_machines-6.1.3.dist-info/RECORD
