Metadata-Version: 2.1
Name: phantasy-machines
Version: 6.1.3
Summary: Machine configuration files for PHANTASY
Home-page: https://github.com/phantasy-project/phantasy-machines
Author: Tong Zhang
Author-email: zhangt@frib.msu.edu
License: UNKNOWN
Platform: UNKNOWN
Classifier: Programming Language :: Python
Classifier: License :: OSI Approved :: MIT License
Classifier: Operating System :: OS Independent
License-File: LICENSE
